{
  "1": [
    {
      "kind": "ItemAttributesRendererInterface@v1",
      "data": {
        "dna": [
          "41ec1e832dcfcc3236de0167cfac8a9247acc364"
        ],
        "name": "Ape 1",
        "description": "This is a token with \"White\" as Background",
        "attributes": {
          "Background": [
            "White"
          ],
          "Eyes": [
            "Regular"
          ],
          "Hair": [
            "Orange"
          ],
          "Mouth": [
            "Smile"
          ],
          "Skin": [
            "Light"
          ]
        }
      }
    },
    {
      "kind": "StaticLayeredImagesRendererInterface@v1",
      "data": {
        "path": "/workspaces/art-engine-template/cache/_temp/1.png"
      }
    }
  ],
  "2": [
    {
      "kind": "ItemAttributesRendererInterface@v1",
      "data": {
        "dna": [
          "a7b0826bdca50bec6585393b228767183d5c6b57"
        ],
        "name": "Ape 2",
        "description": "This is a token with \"White\" as Background",
        "attributes": {
          "Background": [
            "White"
          ],
          "Eyes": [
            "Regular"
          ],
          "Hair": [
            "Orange"
          ],
          "Mouth": [
            "Smile"
          ],
          "Skin": [
            "Tan"
          ]
        }
      }
    },
    {
      "kind": "StaticLayeredImagesRendererInterface@v1",
      "data": {
        "path": "/workspaces/art-engine-template/cache/_temp/2.png"
      }
    }
  ],
  "3": [
    {
      "kind": "ItemAttributesRendererInterface@v1",
      "data": {
        "dna": [
          "a1135dfafb7ac052e837c0288fd5579c1fb296cc"
        ],
        "name": "Ape 3",
        "description": "This is a token with \"White\" as Background",
        "attributes": {
          "Background": [
            "White"
          ],
          "Eyes": [
            "Regular"
          ],
          "Hair": [
            "Dotted Gold"
          ],
          "Mouth": [
            "Smile"
          ],
          "Skin": [
            "Light"
          ]
        }
      }
    },
    {
      "kind": "StaticLayeredImagesRendererInterface@v1",
      "data": {
        "path": "/workspaces/art-engine-template/cache/_temp/3.png"
      }
    }
  ],
  "4": [
    {
      "kind": "ItemAttributesRendererInterface@v1",
      "data": {
        "dna": [
          "14ca65aaaf41262ee0f5dd1fcecc5621f7d49156"
        ],
        "name": "Ape 4",
        "description": "This is a token with \"White\" as Background",
        "attributes": {
          "Background": [
            "White"
          ],
          "Eyes": [
            "Special"
          ],
          "Hair": [
            "Dotted Gold"
          ],
          "Mouth": [
            "Smile"
          ],
          "Skin": [
            "Light"
          ]
        }
      }
    },
    {
      "kind": "StaticLayeredImagesRendererInterface@v1",
      "data": {
        "path": "/workspaces/art-engine-template/cache/_temp/4.png"
      }
    }
  ],
  "5": [
    {
      "kind": "ItemAttributesRendererInterface@v1",
      "data": {
        "dna": [
          "f44fd8d8fd6614a355bcacc5e3688563ff4c4864"
        ],
        "name": "Ape 5",
        "description": "This is a token with \"White\" as Background",
        "attributes": {
          "Background": [
            "White"
          ],
          "Eyes": [
            "Special"
          ],
          "Hair": [
            "PInk"
          ],
          "Mouth": [
            "Smile"
          ],
          "Skin": [
            "Light"
          ]
        }
      }
    },
    {
      "kind": "StaticLayeredImagesRendererInterface@v1",
      "data": {
        "path": "/workspaces/art-engine-template/cache/_temp/5.png"
      }
    }
  ],
  "6": [
    {
      "kind": "ItemAttributesRendererInterface@v1",
      "data": {
        "dna": [
          "c4380c25d2ab883f59f724ea04e9eaf86b009f84"
        ],
        "name": "Ape 6",
        "description": "This is a token with \"White\" as Background",
        "attributes": {
          "Background": [
            "White"
          ],
          "Eyes": [
            "Regular"
          ],
          "Hair": [
            "Dotted Gold"
          ],
          "Mouth": [
            "Smile"
          ],
          "Skin": [
            "Tan"
          ]
        }
      }
    },
    {
      "kind": "StaticLayeredImagesRendererInterface@v1",
      "data": {
        "path": "/workspaces/art-engine-template/cache/_temp/6.png"
      }
    }
  ],
  "7": [
    {
      "kind": "ItemAttributesRendererInterface@v1",
      "data": {
        "dna": [
          "00fd3569083488398f2672747b3f2a506e76916d"
        ],
        "name": "Ape 7",
        "description": "This is a token with \"White\" as Background",
        "attributes": {
          "Background": [
            "White"
          ],
          "Eyes": [
            "Special"
          ],
          "Hair": [
            "Yellow"
          ],
          "Mouth": [
            "Smile"
          ],
          "Skin": [
            "Tan"
          ]
        }
      }
    },
    {
      "kind": "StaticLayeredImagesRendererInterface@v1",
      "data": {
        "path": "/workspaces/art-engine-template/cache/_temp/7.png"
      }
    }
  ],
  "8": [
    {
      "kind": "ItemAttributesRendererInterface@v1",
      "data": {
        "dna": [
          "46168216c52e9256ea8e0b80eef8b990be42cc14"
        ],
        "name": "Ape 8",
        "description": "This is a token with \"White\" as Background",
        "attributes": {
          "Background": [
            "White"
          ],
          "Eyes": [
            "Regular"
          ],
          "Hair": [
            "Pale"
          ],
          "Mouth": [
            "Smile"
          ],
          "Skin": [
            "Tan"
          ]
        }
      }
    },
    {
      "kind": "StaticLayeredImagesRendererInterface@v1",
      "data": {
        "path": "/workspaces/art-engine-template/cache/_temp/8.png"
      }
    }
  ],
  "9": [
    {
      "kind": "ItemAttributesRendererInterface@v1",
      "data": {
        "dna": [
          "79ea4926543b6357988de2a474b71e4b8dc6b26e"
        ],
        "name": "Ape 9",
        "description": "This is a token with \"White\" as Background",
        "attributes": {
          "Background": [
            "White"
          ],
          "Eyes": [
            "Regular"
          ],
          "Hair": [
            "Dotted Cyan"
          ],
          "Mouth": [
            "Smile"
          ],
          "Skin": [
            "Tan"
          ]
        }
      }
    },
    {
      "kind": "StaticLayeredImagesRendererInterface@v1",
      "data": {
        "path": "/workspaces/art-engine-template/cache/_temp/9.png"
      }
    }
  ],
  "10": [
    {
      "kind": "ItemAttributesRendererInterface@v1",
      "data": {
        "dna": [
          "e19fc1346b556f5f2813f62890b374032840fee7"
        ],
        "name": "Ape 10",
        "description": "This is a token with \"White\" as Background",
        "attributes": {
          "Background": [
            "White"
          ],
          "Eyes": [
            "Special"
          ],
          "Hair": [
            "Pale"
          ],
          "Mouth": [
            "Smile"
          ],
          "Skin": [
            "Light"
          ]
        }
      }
    },
    {
      "kind": "StaticLayeredImagesRendererInterface@v1",
      "data": {
        "path": "/workspaces/art-engine-template/cache/_temp/10.png"
      }
    }
  ]
}